elibs/__init__.py
elibs/tom_ticket/__init__.py
elibs/tom_ticket/api.py
elibs/tom_ticket/models/__init__.py
elibs/tom_ticket/models/client.py
elibs/utils/__init__.py
elibs-1.1.dist-info/METADATA
elibs-1.1.dist-info/WHEEL
elibs-1.1.dist-info/top_level.txt
elibs-1.1.dist-info/RECORD
