Metadata-Version: 2.1
Name: elibs
Version: 1.1
Summary: Biblioteca de integração com o TomTicket
Home-page: UNKNOWN
Author: ellitedev
Author-email: osni@sotech.xyz
License: UNKNOWN
Platform: UNKNOWN
